setup.py
txyam/__init__.py
txyam/client.py
txyam/factory.py
txyam/utils.py
txyam.egg-info/PKG-INFO
txyam.egg-info/SOURCES.txt
txyam.egg-info/dependency_links.txt
txyam.egg-info/requires.txt
txyam.egg-info/top_level.txt
txyam/tests/__init__.py
txyam/tests/test_client.py
txyam/tests/test_factory.py
txyam/tests/utils.py