Metadata-Version: 1.1
Name: txyam
Version: 1.0
Summary: Yet Another Memcached (YAM) client for Twisted.
Home-page: http://github.com/bmuller/txyam
Author: Brian Muller
Author-email: bamuller@gmail.com
License: MIT
Platform: UNKNOWN
Requires: twisted.protocols.memcache
Requires: hash_ring
